boitrann/__init__.py
boitrann/lists.py
boitrann-0.1.4.dist-info/METADATA
boitrann-0.1.4.dist-info/WHEEL
boitrann-0.1.4.dist-info/top_level.txt
boitrann-0.1.4.dist-info/RECORD
