Metadata-Version: 2.4
Name: boitrann
Version: 0.1.4
Summary: Some useful utilities for data structures
Author-email: Tran Quoc Dat <dat.tq6141@gmail.com>
Maintainer-email: Tran Quoc Dat <dat.tq6141@gmail.com>
License-Expression: MIT
Project-URL: repository, https://github.com/boitrann/boitrann
Classifier: Programming Language :: Python :: 3
Classifier: Operating System :: OS Independent
Requires-Python: >=3.8
